cprint.py
avilabsutils_cprint-0.0.3.dist-info/METADATA
avilabsutils_cprint-0.0.3.dist-info/WHEEL
avilabsutils_cprint-0.0.3.dist-info/top_level.txt
avilabsutils_cprint-0.0.3.dist-info/RECORD
