Metadata-Version: 2.1
Name: avilabsutils-cprint
Version: 0.0.3
Summary: A bunch of convenience color print functions.
Home-page: https://github.com/avilay/utils/cprint
Author: Avilay Parekh
Author-email: avilay@gmail.com
Classifier: Programming Language :: Python :: 3
Classifier: License :: OSI Approved :: MIT License
Classifier: Operating System :: OS Independent
Requires-Python: >=3.6
Requires-Dist: click
